jupyter_copilot/__init__.py
jupyter_copilot/_version.py
jupyter_copilot/handlers.py
jupyter_copilot/lsp.py
jupyter_copilot/dist/crypt32.node
jupyter_copilot/dist/language-server.js
jupyter_copilot/dist/tree-sitter-go.wasm
jupyter_copilot/dist/tree-sitter-javascript.wasm
jupyter_copilot/dist/tree-sitter-python.wasm
jupyter_copilot/dist/tree-sitter-ruby.wasm
jupyter_copilot/dist/tree-sitter-tsx.wasm
jupyter_copilot/dist/tree-sitter-typescript.wasm
jupyter_copilot/dist/tree-sitter.wasm
jupyter_copilot/dist/compiled/darwin/arm64/kerberos.node
jupyter_copilot/dist/compiled/darwin/x64/kerberos.node
jupyter_copilot/dist/compiled/linux/arm64/kerberos.node
jupyter_copilot/dist/compiled/linux/x64/kerberos.node
jupyter_copilot/dist/compiled/win32/x64/kerberos.node
jupyter_copilot/dist/resources/cl100k_base.tiktoken
jupyter_copilot/dist/resources/o200k_base.tiktoken
jupyter_copilot/labextension/package.json
jupyter_copilot/labextension/schemas/jupyter_copilot/package.json.orig
jupyter_copilot/labextension/schemas/jupyter_copilot/plugin.json
jupyter_copilot/labextension/static/487.3d4de65d6d9043f1af0b.js
jupyter_copilot/labextension/static/728.9cdef5a4a4a1f9516b8a.js
jupyter_copilot/labextension/static/remoteEntry.66b7a4ec72ecf280862f.js
jupyter_copilot/labextension/static/style.js
jupyter_copilot/labextension/static/third-party-licenses.json
jupyter_copilot/dist/crypt32.node
jupyter_copilot/dist/language-server.js
jupyter_copilot/dist/tree-sitter-go.wasm
jupyter_copilot/dist/tree-sitter-javascript.wasm
jupyter_copilot/dist/tree-sitter-python.wasm
jupyter_copilot/dist/tree-sitter-ruby.wasm
jupyter_copilot/dist/tree-sitter-tsx.wasm
jupyter_copilot/dist/tree-sitter-typescript.wasm
jupyter_copilot/dist/tree-sitter.wasm
jupyter_copilot/dist/compiled/darwin/arm64/kerberos.node
jupyter_copilot/dist/compiled/darwin/x64/kerberos.node
jupyter_copilot/dist/compiled/linux/arm64/kerberos.node
jupyter_copilot/dist/compiled/linux/x64/kerberos.node
jupyter_copilot-0.1.5.dist-info/METADATA
jupyter_copilot-0.1.5.dist-info/WHEEL
jupyter_copilot-0.1.5.dist-info/licenses/LICENSE
jupyter_copilot-0.1.5.dist-info/RECORD
