Metadata-Version: 2.4
Name: jupyter_copilot
Version: 0.1.5
Dynamic: Keywords
Summary: GitHub Copilot for Jupyter
Project-URL: Homepage, https://github.com/baolong281/jupyter-copilot
Project-URL: Bug Tracker, https://github.com/baolong281/jupyter-copilot/issues
Project-URL: Repository, https://github.com/baolong281/jupyter-copilot.git
Author-email: jupyter_copilot <dylanhuyn@gmail.com>
License: Copyright (c) 2018 jupyter_copilot
License-File: LICENSE
Classifier: Framework :: Jupyter
Classifier: Framework :: Jupyter :: JupyterLab
Classifier: Framework :: Jupyter :: JupyterLab :: 4
Classifier: Framework :: Jupyter :: JupyterLab :: Extensions
Classifier: Framework :: Jupyter :: JupyterLab :: Extensions :: Prebuilt
Classifier: License :: OSI Approved :: MIT License
Classifier: Programming Language :: Python
Classifier: Programming Language :: Python :: 3
Classifier: Programming Language :: Python :: 3.8
Classifier: Programming Language :: Python :: 3.9
Classifier: Programming Language :: Python :: 3.10
Classifier: Programming Language :: Python :: 3.11
Classifier: Programming Language :: Python :: 3.12
Requires-Python: >=3.8
Requires-Dist: jupyter-server<3,>=2.0.1
